[
  {
    "__type__": "cc.Prefab",
    "_name": "NodeArrow",
    "root": {
      "__id__": 1
    },
    "node": {
      "__id__": 1
    },
    "data": {
      "__id__": 1
    },
    "optimizationPolicy": 0,
    "asyncLoadAssets": false,
    "readonly": false
  },
  {
    "__type__": "cc.Node",
    "_name": "NodeArrow",
    "_groupIndex": 1,
    "groupIndex": 1,
    "_components": [
      {
        "__type__": "cc.Sprite",
        "node": {
          "__id__": 1
        },
        "_materials": [
          {
            "__uuid__": "eca5d2f2-8ef6-41c2-bbe6-f9c79d09c432"
          }
        ],
        "_spriteFrame": {
          "__uuid__": "133b7754-8e72-49e9-a215-fab5e945e88a"
        }
      }
    ],
    "_prefab": {
      "__type__": "cc.PrefabInfo",
      "root": {
        "__id__": 1
      }
    },
    "_contentSize": {
      "__type__": "cc.Size",
      "width": 129,
      "height": 16
    },
    "_anchorPoint": {
      "__type__": "cc.Vec2",
      "x": 1,
      "y": 0.5
    },
    "_trs": {
      "__type__": "TypedArray",
      "ctor": "Float64Array",
      "array": [
        0,
        0,
        0,
        0,
        0,
        -0.7071067811865475,
        0.7071067811865476,
        1,
        1,
        1
      ]
    },
    "_eulerAngles": {
      "__type__": "cc.Vec3",
      "x": 0,
      "y": 0,
      "z": -90
    }
  }
]